django_favicon_plus_reloaded-1.2.3.dist-info/licenses/AUTHORS.txt
django_favicon_plus_reloaded-1.2.3.dist-info/licenses/LICENSE
favicon/__init__.py
favicon/admin.py
favicon/models.py
favicon/migrations/0001_initial.py
favicon/migrations/0002_favicon_site.py
favicon/migrations/0003_site_manager.py
favicon/migrations/0004_faviconimg_favicon_size_rel_unique.py
favicon/migrations/0005_leftover_changes.py
favicon/migrations/__init__.py
favicon/templatetags/__init__.py
favicon/templatetags/favtags.py
django_favicon_plus_reloaded-1.2.3.dist-info/METADATA
django_favicon_plus_reloaded-1.2.3.dist-info/WHEEL
django_favicon_plus_reloaded-1.2.3.dist-info/top_level.txt
django_favicon_plus_reloaded-1.2.3.dist-info/RECORD
