Metadata-Version: 2.4
Name: django-favicon-plus-reloaded
Version: 1.2.3
Summary: Simple Django app which allows you to upload a image and it renders a wide variety for html link tags to display the favicon
Home-page: https://edugit.org/AlekSIS/libs/django-favicon-plus
Author: arteria GmbH
Author-email: arteria@arteria.ch
Maintainer: AlekSIS Team
Maintainer-email: aleksis-dev@lists.teckids.org
License: MIT
Classifier: Development Status :: 5 - Production/Stable
Classifier: Environment :: Web Environment
Classifier: Framework :: Django
Classifier: Intended Audience :: Developers
Classifier: License :: OSI Approved :: MIT License
Classifier: Operating System :: OS Independent
Classifier: Programming Language :: Python
Classifier: Programming Language :: Python :: 3
Classifier: Programming Language :: Python :: 3.8
Classifier: Programming Language :: Python :: 3.9
Classifier: Programming Language :: Python :: 3.10
Classifier: Programming Language :: Python :: 3.11
Classifier: Programming Language :: Python :: 3.12
Classifier: Topic :: Internet :: WWW/HTTP
Classifier: Topic :: Internet :: WWW/HTTP :: Dynamic Content
License-File: LICENSE
License-File: AUTHORS.txt
Requires-Dist: django<6.0,>=4.2.0
Requires-Dist: pillow<12,>=11.2.1
Dynamic: author
Dynamic: author-email
Dynamic: classifier
Dynamic: description
Dynamic: description-content-type
Dynamic: home-page
Dynamic: license
Dynamic: license-file
Dynamic: maintainer
Dynamic: maintainer-email
Dynamic: requires-dist
Dynamic: summary
